[
    {
        "key": 1,
        "id": 1,
        "name": "Lori",
        "image": "https://orig00.deviantart.net/2d07/f/2012/205/d/8/random_cute_person_by_hanabananime-d58hbfp.jpg",
        "selected": false,
        "clicks": 0
    
    
    },

    {
        "key": 2,
        "id": 2,
        "name":"John",
        "image": "https://pm1.narvii.com/6513/1db0baedd1af698584b69b096ca513b7c6b03657_hq.jpg",
        "selected": false,
        "clicks": 0

    },

    {
        "key": 3,
        "id": 3,
        "name": "Connor",
        "image":"https://i.pinimg.com/originals/8e/b0/b6/8eb0b6daf565bec66b764b7d2c0cd500.jpg",
        "selected": false,
        "clicks": 0
        

    },

    {
        "key": 4,
        "id": 4,
        "name": "Kara",
        "image": "https://vignette.wikia.nocookie.net/detroit-become-human/images/3/3c/Kara_JP_site.png/revision/latest?cb=20180606012238",
        "selected": false,
        "clicks": 0
        
    },

    {
        "key": 5,
        "id": 5,
        "name": "Markus",
        "image": "https://i.ytimg.com/vi/8dZPKI6zoWM/maxresdefault.jpg",
        "selected": false,
        "clicks": 0
    }
]